setup.py
wikiwords/__init__.py
wikiwords/freqdb.py
wikiwords/occdb.py
wikiwords.egg-info/PKG-INFO
wikiwords.egg-info/SOURCES.txt
wikiwords.egg-info/dependency_links.txt
wikiwords.egg-info/not-zip-safe
wikiwords.egg-info/top_level.txt