Metadata-Version: 1.0
Name: wikiwords
Version: 0.5
Summary: Word frequencies in 2012 English Wikipedia
Home-page: http://github.com/iitis/wikiwords
Author: Pawel Foremski
Author-email: pjf@iitis.pl
License: the Wikipedia license + GNU GPL
Platform: UNKNOWN
